setup.py
complex_correlate/__init__.py
complex_correlate/metric.c
complex_correlate/moment.c
complex_correlate/shadow.c
complex_correlate.egg-info/PKG-INFO
complex_correlate.egg-info/SOURCES.txt
complex_correlate.egg-info/dependency_links.txt
complex_correlate.egg-info/top_level.txt