Metadata-Version: 1.0
Name: complex-correlate
Version: 0.12.4
Summary: complex_correlate
Home-page: UNKNOWN
Author: UNKNOWN
Author-email: UNKNOWN
License: UNKNOWN
Keywords: complex_correlate
Platform: any
